{
  "date": "2026-08-11",
  "monthDay": "8/11",
  "season": "Ordinary Time",
  "celebration": {
    "name": "Saint Clare, Virgin",
    "type": "MEMORIAL",
    "quote": "We become what we love and who we love shapes what we become.",
    "description": "A noblewoman who followed St. Francis and founded the Poor Clares, living a life of extreme poverty and contemplative prayer.",
    "image": "https://upload.wikimedia.org/wikipedia/commons/thumb/f/fd/Simone_Martini_047.jpg/500px-Simone_Martini_047.jpg"
  },
  "apiEndpoint": "https://cpbjr.github.io/catholic-readings-api/liturgical-calendar/2026/08-11.json"
}